simple_launch_process.py
simple_launch_process-0.1.1.dist-info/LICENSE.txt
simple_launch_process-0.1.1.dist-info/METADATA
simple_launch_process-0.1.1.dist-info/WHEEL
simple_launch_process-0.1.1.dist-info/top_level.txt
simple_launch_process-0.1.1.dist-info/RECORD
