Metadata-Version: 2.1
Name: simple-launch-process
Version: 0.1.1
Summary: Client library for simple-launch
Author-email: John Wason <wason@wasontech.com>
License: Apache-2.0
Requires-Python: >=3.6
License-File: LICENSE.txt
